tests_cli/__init__.py
tests_cli/test_client_script.py
tests_cli/test_example.py
tests_cli/test_node_cli.py
tests_cli/test_server_cli.py
tests_cli/test_wizard.py
vantage6/cli/__build__
vantage6/cli/__init__.py
vantage6/cli/_version.py
vantage6/cli/cli.py
vantage6/cli/configuration_manager.py
vantage6/cli/configuration_wizard.py
vantage6/cli/globals.py
vantage6/cli/utils.py
vantage6/cli/algorithm/create.py
vantage6/cli/algorithm/update.py
vantage6/cli/algostore/attach.py
vantage6/cli/algostore/files.py
vantage6/cli/algostore/list.py
vantage6/cli/algostore/new.py
vantage6/cli/algostore/remove.py
vantage6/cli/algostore/start.py
vantage6/cli/algostore/stop.py
vantage6/cli/common/decorator.py
vantage6/cli/common/start.py
vantage6/cli/common/utils.py
vantage6/cli/context/__init__.py
vantage6/cli/context/algorithm_store.py
vantage6/cli/context/base_server.py
vantage6/cli/context/node.py
vantage6/cli/context/server.py
vantage6/cli/dev/create.py
vantage6/cli/dev/remove.py
vantage6/cli/dev/start.py
vantage6/cli/dev/stop.py
vantage6/cli/dev/utils.py
vantage6/cli/dev/data/km_dataset.csv
vantage6/cli/dev/data/olympic_athletes_2016.csv
vantage6/cli/node/attach.py
vantage6/cli/node/clean.py
vantage6/cli/node/create_private_key.py
vantage6/cli/node/files.py
vantage6/cli/node/list.py
vantage6/cli/node/new.py
vantage6/cli/node/remove.py
vantage6/cli/node/restart.py
vantage6/cli/node/set_api_key.py
vantage6/cli/node/start.py
vantage6/cli/node/stop.py
vantage6/cli/node/version.py
vantage6/cli/node/common/__init__.py
vantage6/cli/prometheus/monitoring_manager.py
vantage6/cli/prometheus/prometheus.yml
vantage6/cli/rabbitmq/__init__.py
vantage6/cli/rabbitmq/definitions.py
vantage6/cli/rabbitmq/queue_manager.py
vantage6/cli/rabbitmq/rabbitmq.config
vantage6/cli/server/attach.py
vantage6/cli/server/files.py
vantage6/cli/server/import_.py
vantage6/cli/server/list.py
vantage6/cli/server/new.py
vantage6/cli/server/remove.py
vantage6/cli/server/shell.py
vantage6/cli/server/start.py
vantage6-4.13.6.dist-info/METADATA
vantage6-4.13.6.dist-info/WHEEL
vantage6-4.13.6.dist-info/entry_points.txt
vantage6-4.13.6.dist-info/top_level.txt
vantage6-4.13.6.dist-info/RECORD
